arize_toolkit/__init__.py
arize_toolkit/client.py
arize_toolkit/constants.py
arize_toolkit/exceptions.py
arize_toolkit/model_managers.py
arize_toolkit/types.py
arize_toolkit/utils.py
arize_toolkit/extensions/__init__.py
arize_toolkit/extensions/prompt_optimizer/__init__.py
arize_toolkit/extensions/prompt_optimizer/constants.py
arize_toolkit/extensions/prompt_optimizer/meta_prompt.py
arize_toolkit/extensions/prompt_optimizer/prompt_learning_optimizer.py
arize_toolkit/extensions/prompt_optimizer/tiktoken_splitter.py
arize_toolkit/models/__init__.py
arize_toolkit/models/base_models.py
arize_toolkit/models/custom_metrics_models.py
arize_toolkit/models/dashboard_models.py
arize_toolkit/models/data_import_models.py
arize_toolkit/models/llm_utils_models.py
arize_toolkit/models/monitor_models.py
arize_toolkit/models/space_models.py
arize_toolkit/queries/__init__.py
arize_toolkit/queries/basequery.py
arize_toolkit/queries/custom_metric_queries.py
arize_toolkit/queries/dashboard_queries.py
arize_toolkit/queries/data_import_queries.py
arize_toolkit/queries/llm_utils_queries.py
arize_toolkit/queries/model_queries.py
arize_toolkit/queries/monitor_queries.py
arize_toolkit/queries/space_queries.py
arize_toolkit-1.0.8.dist-info/METADATA
arize_toolkit-1.0.8.dist-info/WHEEL
arize_toolkit-1.0.8.dist-info/licenses/LICENSE
arize_toolkit-1.0.8.dist-info/RECORD
