Metadata-Version: 2.4
Name: arize_toolkit
Version: 1.0.8
Summary: A library to interact with Arize AI APIs
Author-email: Duncan McKinnon <dmckinnon@arize.com>
License: MIT
License-File: LICENSE
Keywords: arize,graphql,monitoring,observability
Classifier: Intended Audience :: Developers
Classifier: Programming Language :: Python :: 3.9
Classifier: Programming Language :: Python :: 3.10
Classifier: Programming Language :: Python :: 3.11
Classifier: Programming Language :: Python :: 3.12
Classifier: Programming Language :: Python :: 3.13
Classifier: Topic :: Scientific/Engineering :: Artificial Intelligence
Classifier: Topic :: Software Development :: Libraries :: Python Modules
Requires-Python: <3.14,>=3.9
Requires-Dist: gql<4.0,>=3.0.0
Requires-Dist: pandas<3.0,>=0.25.3
Requires-Dist: pydantic~=2.0
Requires-Dist: requests-toolbelt>=1.0.0
Requires-Dist: requests<3.0,>=2.28.1
Provides-Extra: dev
Requires-Dist: black==25.1.0; extra == 'dev'
Requires-Dist: coverage; extra == 'dev'
Requires-Dist: flake8==7.2.0; extra == 'dev'
Requires-Dist: ipykernel>=6.29.5; extra == 'dev'
Requires-Dist: isort==5.13.2; extra == 'dev'
Requires-Dist: mdformat==0.7.22; extra == 'dev'
Requires-Dist: mkdocs-material>=9.0.0; extra == 'dev'
Requires-Dist: mkdocs>=1.4.0; extra == 'dev'
Requires-Dist: pre-commit==3.5.0; extra == 'dev'
Requires-Dist: pytest; extra == 'dev'
Requires-Dist: pytest-cov; extra == 'dev'
Requires-Dist: pytest-mock; extra == 'dev'
Requires-Dist: snapshottest; (python_version < '3.12') and extra == 'dev'
Provides-Extra: integration
Requires-Dist: python-dotenv; extra == 'integration'
Provides-Extra: prompt-optimizer
Requires-Dist: arize-phoenix-client>=1.0; extra == 'prompt-optimizer'
Requires-Dist: arize-phoenix-evals>=0.22.0; extra == 'prompt-optimizer'
Requires-Dist: tiktoken>=0.9.0; extra == 'prompt-optimizer'
